ecc/ChinesischerRestsatz.py
ecc/ElGammal.py
ecc/Kurven.py
ecc/Menezes_Vanstone_Kryptosystem.py
ecc/Menezes_Vanstone_Streamlit.py
ecc/Menezes_vanstone_Ascii.py
ecc/Streamlit.py
ecc/__init__.py
ecc/elliptischeKurve.py
ecc/endlicheKoerper_Fp.py
ecc/endlicherKoerper_F2n.py
ecc/endlicherKoerper_Fpn.py
ecc/find_irreducible_polynomial.py
ecc/getrandomcurve.py
ecc/laufzeit.py
ecc/rechen_mit_Fp.py
ecc/rechnen_mit_Fpn.py
ecc/schooftest.py
ecc/test.py
ecc/test2.py
ecc/test3.py
ecc/test4.py
ecc/test5.py
ecc/test6.py
ecc/test7.py
ecc/testen.py
Library_elliptic_Curves-0.1.2.dist-info/LICENSE
Library_elliptic_Curves-0.1.2.dist-info/METADATA
Library_elliptic_Curves-0.1.2.dist-info/WHEEL
Library_elliptic_Curves-0.1.2.dist-info/top_level.txt
Library_elliptic_Curves-0.1.2.dist-info/RECORD
