Metadata-Version: 2.1
Name: Library-elliptic-Curves
Version: 0.1.2
Summary: ECC Library
Author: Kaspar Hui
Author-email: <kaspar.hui@bluewin.ch>
Keywords: python,video,stream,video stream,camera stream,sockets
Classifier: Development Status :: 1 - Planning
Classifier: Intended Audience :: Developers
Classifier: Programming Language :: Python :: 3
Classifier: Operating System :: Unix
Classifier: Operating System :: MacOS :: MacOS X
Classifier: Operating System :: Microsoft :: Windows
License-File: LICENSE
